letterboxdpy/avatar.py
letterboxdpy/films.py
letterboxdpy/list.py
letterboxdpy/members.py
letterboxdpy/movie.py
letterboxdpy/search.py
letterboxdpy/url.py
letterboxdpy/user.py
letterboxdpy/watchlist.py
letterboxdpy/constants/project.py
letterboxdpy/constants/selectors.py
letterboxdpy/core/decorators.py
letterboxdpy/core/encoder.py
letterboxdpy/core/exceptions.py
letterboxdpy/core/models.py
letterboxdpy/core/scraper.py
letterboxdpy/pages/movie_details.py
letterboxdpy/pages/movie_lists.py
letterboxdpy/pages/movie_members.py
letterboxdpy/pages/movie_profile.py
letterboxdpy/pages/movie_reviews.py
letterboxdpy/pages/movie_similar.py
letterboxdpy/pages/user_activity.py
letterboxdpy/pages/user_diary.py
letterboxdpy/pages/user_films.py
letterboxdpy/pages/user_likes.py
letterboxdpy/pages/user_list.py
letterboxdpy/pages/user_lists.py
letterboxdpy/pages/user_network.py
letterboxdpy/pages/user_profile.py
letterboxdpy/pages/user_reviews.py
letterboxdpy/pages/user_tags.py
letterboxdpy/pages/user_watchlist.py
letterboxdpy/utils/activity_extractor.py
letterboxdpy/utils/date_utils.py
letterboxdpy/utils/lists_extractor.py
letterboxdpy/utils/movies_extractor.py
letterboxdpy/utils/utils_csv.py
letterboxdpy/utils/utils_directory.py
letterboxdpy/utils/utils_file.py
letterboxdpy/utils/utils_parser.py
letterboxdpy/utils/utils_string.py
letterboxdpy/utils/utils_transform.py
letterboxdpy/utils/utils_url.py
letterboxdpy-6.3.0.dist-info/METADATA
letterboxdpy-6.3.0.dist-info/WHEEL
letterboxdpy-6.3.0.dist-info/licenses/LICENSE
letterboxdpy-6.3.0.dist-info/RECORD
