Metadata-Version: 2.4
Name: letterboxdpy
Version: 6.3.0
Summary: A letterboxd webscraper
Project-URL: Repository, https://github.com/nmcassa/letterboxdpy
Project-URL: Documentation, https://github.com/nmcassa/letterboxdpy
Project-URL: Bug Tracker, https://github.com/nmcassa/letterboxdpy/issues
Project-URL: Source Code, https://github.com/nmcassa/letterboxdpy/archive/refs/heads/main.zip
Author-email: Nicholas Cassarino <nmcassa804@outlook.com>
Maintainer-email: FastFingertips <fastfingertips@gmail.com>
License-Expression: MIT
License-File: LICENSE
Keywords: diary,film,letterboxd,movie,rating,review,watchlist,webscraper
Classifier: License :: OSI Approved :: MIT License
Classifier: Operating System :: OS Independent
Classifier: Programming Language :: Python :: 3
Requires-Python: >=3.9
Requires-Dist: beautifulsoup4>=4.12.3
Requires-Dist: curl-cffi>=0.14.0
Requires-Dist: fastfingertips>=0.1.3
Requires-Dist: lxml>=5.1.0
